{
  "uid": "ai_scout_bot",
  "cash": 175407.0,
  "positions": {
    "0050.TW": {
      "shares": 1000,
      "entry_price": 94.6,
      "entry_cost": 94735.0,
      "entry_date": "2026-05-05",
      "entry_time": "2026-05-05 09:22:51",
      "entry_verdict": "Bullish",
      "entry_confidence": 80,
      "target_price": 100.0,
      "stop_loss": 88.03,
      "ai_original_stop": 88.0,
      "stop_adjustment_note": "tightened (AI stop too loose: 6.60 > 6.57)",
      "expected_hold_days": 20,
      "signal_strength": "strong",
      "name": "YUANTA SECURITIES INV TRUST CO ",
      "entry_market_regime": "bull",
      "entry_taiex": 38926.63,
      "highest_price": 96.6,
      "entry_atr": 2.19,
      "trailing_stop": null,
      "trailing_activated": false,
      "max_profit_pct": 2.11,
      "profit_locked": false,
      "profit_lock_stop": null,
      "conf_low_count": 0,
      "last_confidence": 85,
      "conf_flip_count": 0,
      "rs_weak_count": 0,
      "last_rs": {
        "vs_taiex_pct": 0.31,
        "label": "平盤"
      }
    },
    "2441.TW": {
      "shares": 1000,
      "entry_price": 92.4,
      "entry_cost": 92532.0,
      "entry_date": "2026-05-05",
      "entry_time": "2026-05-05 09:22:51",
      "entry_verdict": "Bullish",
      "entry_confidence": 90,
      "target_price": 105.0,
      "stop_loss": 83.93,
      "ai_original_stop": 85.0,
      "stop_adjustment_note": "widened (AI stop too tight: 7.40 < 8.48)",
      "expected_hold_days": 12,
      "signal_strength": "strong",
      "name": "GREATEK ELECTRONICS INC",
      "entry_market_regime": "bull",
      "entry_taiex": 38926.63,
      "highest_price": 96.0,
      "entry_atr": 5.65,
      "trailing_stop": null,
      "trailing_activated": false,
      "max_profit_pct": 3.9,
      "profit_locked": false,
      "profit_lock_stop": null,
      "conf_low_count": 0,
      "last_confidence": 80,
      "conf_flip_count": 0,
      "rs_weak_count": 0,
      "last_rs": {
        "vs_taiex_pct": 1.35,
        "label": "跟漲"
      }
    },
    "00929.TW": {
      "shares": 4000,
      "entry_price": 23.4,
      "entry_cost": 93733.0,
      "entry_date": "2026-05-05",
      "entry_time": "2026-05-05 09:37:45",
      "entry_verdict": "Bullish",
      "entry_confidence": 90,
      "target_price": 24.5,
      "stop_loss": 21.78,
      "ai_original_stop": 21.5,
      "stop_adjustment_note": "tightened (AI stop too loose: 1.90 > 1.62)",
      "expected_hold_days": 10,
      "signal_strength": "strong",
      "name": "FUH HWA SECURITIES INVESTMENT T",
      "entry_market_regime": "bull",
      "entry_taiex": 38926.63,
      "highest_price": 24.48,
      "entry_atr": 0.54,
      "trailing_stop": null,
      "trailing_activated": false,
      "max_profit_pct": 4.62,
      "profit_locked": false,
      "profit_lock_stop": null,
      "conf_low_count": 0,
      "last_confidence": 90,
      "conf_flip_count": 0,
      "rs_weak_count": 0,
      "last_rs": {
        "vs_taiex_pct": 2.66,
        "label": "強勢"
      }
    },
    "00881.TW": {
      "shares": 2000,
      "entry_price": 49.04,
      "entry_cost": 98220.0,
      "entry_date": "2026-05-05",
      "entry_time": "2026-05-05 09:51:08",
      "entry_verdict": "Bullish",
      "entry_confidence": 90,
      "target_price": 52.0,
      "stop_loss": 45.5,
      "ai_original_stop": 45.5,
      "stop_adjustment_note": "unchanged",
      "expected_hold_days": 12,
      "signal_strength": "strong",
      "name": "CATHAY SECS INV TRUST CO LTD TA",
      "entry_market_regime": "bull",
      "entry_taiex": 38926.63,
      "highest_price": 49.23,
      "entry_atr": 1.19,
      "trailing_stop": null,
      "trailing_activated": false,
      "max_profit_pct": 0.39,
      "profit_locked": false,
      "profit_lock_stop": null,
      "conf_low_count": 0,
      "last_confidence": 90,
      "conf_flip_count": 0,
      "rs_weak_count": 0,
      "last_rs": {
        "vs_taiex_pct": 0.04,
        "label": "平盤"
      }
    },
    "2330.TW": {
      "shares": 43,
      "entry_price": 2275.0,
      "entry_cost": 97964.0,
      "entry_date": "2026-05-06",
      "entry_time": "2026-05-06 09:54:55",
      "entry_verdict": "Bullish",
      "entry_confidence": 85,
      "target_price": 2450.0,
      "stop_loss": 2084.02,
      "ai_original_stop": 2050.0,
      "stop_adjustment_note": "tightened (AI stop too loose: 225.00 > 190.98)",
      "expected_hold_days": 15,
      "signal_strength": "strong",
      "name": "TAIWAN SEMICONDUCTOR MANUFACTUR",
      "entry_market_regime": "bull",
      "entry_taiex": 40705.14,
      "highest_price": 2330.0,
      "entry_atr": 63.66,
      "trailing_stop": null,
      "trailing_activated": false,
      "max_profit_pct": 2.42,
      "profit_locked": false,
      "profit_lock_stop": null,
      "conf_low_count": 0,
      "last_confidence": 85,
      "conf_flip_count": 0,
      "rs_weak_count": 0,
      "last_rs": {
        "vs_taiex_pct": 1.13,
        "label": "跟漲"
      }
    },
    "2891.TW": {
      "shares": 1000,
      "entry_price": 55.1,
      "entry_cost": 55179.0,
      "entry_date": "2026-05-06",
      "entry_time": "2026-05-06 10:53:59",
      "entry_verdict": "Bullish",
      "entry_confidence": 85,
      "target_price": 58.0,
      "stop_loss": 52.0,
      "ai_original_stop": 52.0,
      "stop_adjustment_note": "unchanged",
      "expected_hold_days": 12,
      "signal_strength": "strong",
      "name": "CTBC FINANCIAL HOLDINGS COMPANY",
      "entry_market_regime": "bull",
      "entry_taiex": 40705.14,
      "highest_price": 55.1,
      "entry_atr": 1.22,
      "trailing_stop": null,
      "trailing_activated": false,
      "max_profit_pct": 0,
      "profit_locked": false,
      "profit_lock_stop": null,
      "conf_low_count": 0,
      "last_confidence": 70,
      "conf_flip_count": 0,
      "rs_weak_count": 0,
      "last_rs": {
        "vs_taiex_pct": 1.33,
        "label": "跟漲"
      }
    },
    "00891.TW": {
      "shares": 3000,
      "entry_price": 33.29,
      "entry_cost": 100012.0,
      "entry_date": "2026-05-06",
      "entry_time": "2026-05-06 10:53:59",
      "entry_verdict": "Bullish",
      "entry_confidence": 80,
      "target_price": 34.5,
      "stop_loss": 30.65,
      "ai_original_stop": 30.5,
      "stop_adjustment_note": "tightened (AI stop too loose: 2.79 > 2.64)",
      "expected_hold_days": 7,
      "signal_strength": "strong",
      "name": "CTBC INVESTMENTS CO LTD TAIWAN ",
      "entry_market_regime": "bull",
      "entry_taiex": 40705.14,
      "highest_price": 33.76,
      "entry_atr": 0.88,
      "trailing_stop": null,
      "trailing_activated": false,
      "max_profit_pct": 1.41,
      "profit_locked": false,
      "profit_lock_stop": null,
      "conf_low_count": 0,
      "last_confidence": 85,
      "conf_flip_count": 0,
      "rs_weak_count": 0,
      "last_rs": {
        "vs_taiex_pct": 0.56,
        "label": "跟漲"
      }
    },
    "00940.TW": {
      "shares": 9000,
      "entry_price": 10.85,
      "entry_cost": 97789.0,
      "entry_date": "2026-05-06",
      "entry_time": "2026-05-06 15:27:35",
      "entry_verdict": "Bullish",
      "entry_confidence": 85,
      "target_price": 11.2,
      "stop_loss": 10.4,
      "ai_original_stop": 10.1,
      "stop_adjustment_note": "tightened (AI stop too loose: 0.75 > 0.45)",
      "expected_hold_days": 10,
      "signal_strength": "strong",
      "name": "YUANTA SECURITIES INV TRUST CO ",
      "entry_market_regime": "bull",
      "entry_taiex": 41238.49,
      "highest_price": 10.97,
      "entry_atr": 0.15,
      "trailing_stop": null,
      "trailing_activated": false,
      "max_profit_pct": 1.11,
      "profit_locked": false,
      "profit_lock_stop": null,
      "conf_low_count": 0,
      "last_confidence": 60,
      "conf_flip_count": 13,
      "rs_weak_count": 0,
      "last_rs": {
        "vs_taiex_pct": -0.45,
        "label": "平盤"
      }
    },
    "00918.TW": {
      "shares": 4000,
      "entry_price": 24.84,
      "entry_cost": 99502.0,
      "entry_date": "2026-05-07",
      "entry_time": "2026-05-07 10:22:07",
      "entry_verdict": "Bullish",
      "entry_confidence": 80,
      "target_price": 26.0,
      "stop_loss": 23.76,
      "ai_original_stop": 23.5,
      "stop_adjustment_note": "tightened (AI stop too loose: 1.34 > 1.08)",
      "expected_hold_days": 12,
      "signal_strength": "strong",
      "name": "UOB ASSET MANAGEMENT (TAIWAN)CO",
      "entry_market_regime": "bull",
      "entry_taiex": 40769.29,
      "highest_price": 24.89,
      "entry_atr": 0.36,
      "trailing_stop": null,
      "trailing_activated": false,
      "max_profit_pct": 0.2,
      "profit_locked": false,
      "profit_lock_stop": null,
      "conf_low_count": 0,
      "last_confidence": 80,
      "conf_flip_count": 0,
      "rs_weak_count": 0,
      "last_rs": {
        "vs_taiex_pct": 0.28,
        "label": "平盤"
      }
    }
  },
  "history": [
    {
      "sym": "00919.TW",
      "name": "CAPITAL INV TRUST CORP CAP TIP ",
      "shares": 3000,
      "entry_price": 24.09,
      "entry_date": "2026-05-05",
      "exit_price": 24.83,
      "exit_date": "2026-05-06",
      "exit_time": "2026-05-06 09:22:01",
      "exit_reason": "target",
      "pnl": 1788.0,
      "pnl_pct": 2.47,
      "hold_days": 1,
      "entry_confidence": 85,
      "entry_verdict": "Bullish",
      "signal_strength": "strong",
      "mode": "fixed",
      "adjustments_count": 0,
      "entry_market_regime": "bull",
      "exit_market_regime": "bull",
      "highest_price": 24.83,
      "trailing_stop_at_exit": null,
      "trailing_activated": false,
      "max_profit_pct": 3.07,
      "profit_locked": false,
      "profit_lock_stop_at_exit": null
    },
    {
      "sym": "0056.TW",
      "name": "YUANTA SECURITIES INV TRUST CO ",
      "shares": 2000,
      "entry_price": 42.62,
      "entry_date": "2026-05-07",
      "exit_price": 44.52,
      "exit_date": "2026-05-07",
      "exit_time": "2026-05-07 10:07:22",
      "exit_reason": "target",
      "pnl": 3285.0,
      "pnl_pct": 3.85,
      "hold_days": 0,
      "entry_confidence": 80,
      "entry_verdict": "Bullish",
      "signal_strength": "strong",
      "mode": "fixed",
      "adjustments_count": 0,
      "entry_market_regime": "bull",
      "exit_market_regime": "bull",
      "highest_price": 44.52,
      "trailing_stop_at_exit": null,
      "trailing_activated": false,
      "max_profit_pct": 4.46,
      "profit_locked": false,
      "profit_lock_stop_at_exit": null
    }
  ],
  "stats": {
    "total_trades": 2,
    "win_trades": 2,
    "total_pnl": 5073.0
  },
  "cooldowns": {
    "00919.TW": "2026-05-13",
    "0056.TW": "2026-05-14"
  },
  "pending_confirms": {
    "2330.TW": {
      "count": 15,
      "last_seen": "2026-05-07 12:53:20"
    },
    "2303.TW": {
      "count": 15,
      "last_seen": "2026-05-07 12:53:20"
    },
    "2344.TW": {
      "count": 15,
      "last_seen": "2026-05-07 12:53:20"
    },
    "3026.TW": {
      "count": 15,
      "last_seen": "2026-05-07 12:53:20"
    },
    "00919.TW": {
      "count": 13,
      "last_seen": "2026-05-07 12:53:20"
    },
    "0056.TW": {
      "count": 13,
      "last_seen": "2026-05-07 12:53:20"
    },
    "2317.TW": {
      "count": 5,
      "last_seen": "2026-05-07 12:53:20"
    },
    "00918.TW": {
      "count": 2,
      "last_seen": "2026-05-07 12:53:20"
    }
  },
  "settings": {
    "initial_capital": 1000000,
    "max_positions": 10,
    "per_position_cap": 100000,
    "confidence_threshold": 80,
    "cooldown_trading_days": 5,
    "min_hold_trading_days": 3,
    "stale_exit_trading_days": 10,
    "daily_entry_limit": 5,
    "auto_trade": true,
    "enable_ai_review": true,
    "ai_curated_watchlist": true,
    "profit_lock_arm_pct": 7,
    "profit_lock_floor_pct": 3,
    "ma5_extension_limit_pct": 3,
    "sector_filter_mode": "weak_only"
  },
  "engine_updated_at": "2026-05-07 12:53:20",
  "has_password": false,
  "last_engine_status": {
    "timestamp": "2026-05-07 12:53:20",
    "summary": "等待第二次 Bullish 確認（8 檔）",
    "reason_zh": "已偵測到 8 檔訊號，需再一次 Bullish 才會進場：2330.TW, 2303.TW, 2344.TW",
    "exits": 0,
    "entries": 0,
    "reasons_breakdown": {
      "already_held": 2,
      "ma5_extended_6.3_over_5.0": 1,
      "price_above_entry": 2,
      "conf_below_80": 3,
      "verdict_Neutral": 4,
      "cooldown_until_2026-05-13": 1,
      "cooldown_until_2026-05-14": 1,
      "ma5_extended_11.0_over_5.0": 1,
      "verdict_Bearish": 2
    },
    "pending_confirms_count": 8,
    "evaluated_symbols": 17,
    "market_regime": "bull",
    "market_regime_zh": "多頭（站上 20MA）",
    "taiex": 40769.29,
    "taiex_ma20": 37430.7,
    "taiex_ma60": 34598.11,
    "dynamic_threshold": 80,
    "base_threshold": 80,
    "regime_winrate": null,
    "regime_sample_count": 2,
    "macro_risk": {
      "level": "normal",
      "score": 0,
      "triggers": [],
      "details": {
        "vix": 17.39,
        "us10y": 4.36,
        "usd_twd": 31.4,
        "nvda_change": 5.77,
        "sox_change": 4.48,
        "taiex_change": 0.16
      }
    },
    "macro_level_zh": "正常",
    "sector_concentration": {
      "半導體": 1
    }
  },
  "initialized": true
}