{
  "picks": [
    {
      "symbol": "2891.TW",
      "name": "中信金",
      "category": "權值股 / 金融",
      "reason": "外資與投信同步買超，籌碼穩定且漲幅溫和，適合中長線資產配置。"
    },
    {
      "symbol": "2356.TW",
      "name": "英業達",
      "category": "權值股 / 電子代工",
      "reason": "獲外資大舉買超，漲幅僅3.58%屬健康走勢，具備產業轉型題材。"
    },
    {
      "symbol": "2301.TW",
      "name": "光寶科",
      "category": "權值股 / 電子零組件",
      "reason": "外資買超且漲幅適中，股價位階合理，長期營運穩定度高。"
    },
    {
      "symbol": "2330.TW",
      "name": "台積電",
      "category": "權值股 / 半導體",
      "reason": "雖遭外資調節，但屬長線護盤核心，回檔提供中長線佈局機會。"
    },
    {
      "symbol": "2883.TW",
      "name": "凱基金",
      "category": "權值股 / 金融",
      "reason": "外資持續買超，股價持平無過熱疑慮，具備長期領息與防禦價值。"
    },
    {
      "symbol": "5469.TW",
      "name": "瀚宇博",
      "category": "中型股 / PCB",
      "reason": "投信與外資共同買超，今日股價持平，籌碼面呈現蓄勢待發狀態。"
    },
    {
      "symbol": "3706.TW",
      "name": "神達",
      "category": "中型股 / 電腦週邊",
      "reason": "投信持續加碼，漲幅僅1.04%，避開短線噴出風險，成長趨勢明確。"
    },
    {
      "symbol": "2367.TW",
      "name": "燿華",
      "category": "中型股 / PCB",
      "reason": "投信積極買超，漲幅3.47%屬溫和上漲，籌碼集中度提升。"
    },
    {
      "symbol": "2515.TW",
      "name": "中工",
      "category": "中型股 / 營建",
      "reason": "投信買超，漲幅小於1%，避開過熱風險，具備穩健獲利與資產題材。"
    },
    {
      "symbol": "2812.TW",
      "name": "台中銀",
      "category": "中型股 / 金融",
      "reason": "投信持續買超，股價波動極小，符合中長線穩健投資與抗通膨需求。"
    },
    {
      "symbol": "1605.TW",
      "name": "華新",
      "category": "中型股 / 電線電纜",
      "reason": "外資買超力道強勁，漲幅5.08%尚在可控範圍，具備原物料行情。"
    },
    {
      "symbol": "2498.TW",
      "name": "宏達電",
      "category": "中型股 / 通訊網路",
      "reason": "外資買超且漲幅適中，技術面轉強，適合中長線佈局轉機行情。"
    },
    {
      "symbol": "1710.TW",
      "name": "東聯",
      "category": "中型股 / 化學工業",
      "reason": "外資買超，雖漲幅接近警戒線，但產業具備循環復甦潛力，列入觀察。"
    },
    {
      "symbol": "2303.TW",
      "name": "聯電",
      "category": "權值股 / 半導體",
      "reason": "外資雖賣超但股價微漲，顯示買盤承接力道強，具長線價值。"
    },
    {
      "symbol": "3481.TW",
      "name": "群創",
      "category": "中型股 / 面板",
      "reason": "外資賣超但股價上漲，顯示籌碼換手，適合中長線低檔佈局。"
    },
    {
      "symbol": "2405.TW",
      "name": "輔信",
      "category": "中型股 / 電腦週邊",
      "reason": "外資賣超但股價上漲，籌碼面具備抗跌性，適合中長線價值投資。"
    },
    {
      "symbol": "3702.TW",
      "name": "大聯大",
      "category": "權值股 / 電子通路",
      "reason": "外資調節但跌幅有限，作為產業景氣風向球，具中長線佈局價值。"
    }
  ],
  "rationale": "本投資組合以「穩健成長」與「籌碼穩定」為核心，嚴格避開單日漲幅超過8%的過熱股，確保進場成本的安全性。選股策略納入權值股與中型潛力股各半，兼顧流動性與爆發力。產業配置涵蓋半導體、金融、PCB、營建、化學及電子通路，大幅降低單一產業波動風險。優先挑選法人（外資、投信）同步買超或籌碼換手跡象明顯的標的，剔除法人賣超嚴重且基本面存疑的個股，以期在震盪市況中達成資產增值。",
  "sectors_covered": [
    "半導體",
    "金融",
    "電子代工",
    "PCB",
    "營建",
    "化學工業",
    "電子通路"
  ],
  "generated_at": "2026-07-02 10:15:46",
  "radar_date": "20260701"
}