{
  "picks": [
    {
      "symbol": "2887.TW",
      "name": "台新新光金",
      "category": "權值股 / 金融",
      "reason": "連續3日上榜且獲外資與投信雙重買超，籌碼結構穩定，具備中長線金融整合題材。"
    },
    {
      "symbol": "00878.TW",
      "name": "國泰永續高股息",
      "category": "權值股 / ETF",
      "reason": "連續6日獲法人買超，作為中長線資產配置，提供穩定現金流與抗波動能力。"
    },
    {
      "symbol": "2882.TW",
      "name": "國泰金",
      "category": "權值股 / 金融",
      "reason": "外資買超前段班，且股價溫和上漲，避開了短線過熱風險，適合長期持有。"
    },
    {
      "symbol": "2382.TW",
      "name": "廣達",
      "category": "權值股 / 電子代工",
      "reason": "雖當日股價修正，但獲投信強力買超，顯示法人看好其長線AI伺服器佈局，適合逢低佈局。"
    },
    {
      "symbol": "1402.TW",
      "name": "遠東新",
      "category": "權值股 / 傳產",
      "reason": "獲投信買超支持，股價走勢穩健，產業屬性具備防禦價值，符合資產配置多元化需求。"
    },
    {
      "symbol": "2105.TW",
      "name": "正新",
      "category": "中型潛力股 / 橡膠",
      "reason": "投信持續買超且股價持平，無短線噴出風險，籌碼籌碼沉澱穩定，具長線成長潛力。"
    },
    {
      "symbol": "4938.TW",
      "name": "和碩",
      "category": "中型潛力股 / 電子代工",
      "reason": "投信積極佈局，股價修正提供較佳進場點，避開短線噴出股，適合中長線價值投資。"
    },
    {
      "symbol": "2542.TW",
      "name": "興富發",
      "category": "中型潛力股 / 營建",
      "reason": "獲投信買超，股價表現平穩，營建業具備抗通膨特性，適合納入多元產業觀察名單。"
    },
    {
      "symbol": "2855.TW",
      "name": "統一證",
      "category": "中型潛力股 / 金融",
      "reason": "投信買超且股價溫和上漲，受惠於資本市場交易活絡，獲利展望具備中長線支撐。"
    },
    {
      "symbol": "1513.TW",
      "name": "中興電",
      "category": "中型潛力股 / 重電",
      "reason": "量能溫和放大且股價上漲，符合綠能轉型長線趨勢，籌碼結構未見過熱跡象。"
    }
  ],
  "rationale": "本投資組合以中長線價值成長為核心，嚴格過濾掉短線噴出過熱股與法人買超但股價異常下跌的籌碼陷阱。策略上，我們優先鎖定連續多日獲法人買超的個股以確保籌碼穩定性，並透過權值股與中型潛力股的混搭，兼顧資產配置的防禦力與成長性。產業選擇涵蓋金融、電子代工、營建、重電及傳產，有效分散單一產業風險。所有入選標的均避開單日漲幅超過8%的過熱訊號，確保進場成本的合理性，適合長期追蹤佈局。",
  "sectors_covered": [
    "金融",
    "電子代工",
    "傳產",
    "營建",
    "重電",
    "ETF"
  ],
  "generated_at": "2026-06-10 12:05:18",
  "radar_date": "20260605"
}