{
  "session": "midday",
  "show_name": "台股盤中快訊",
  "title": "台股再創高點！盤中重點與個股動向",
  "greeting": "大家好，歡迎收看『台股盤中快訊』，我是您的主播。現在時間是10點12分，讓我們一起看看台股的最新動態。",
  "sections": [
    {
      "heading": "國際局勢快覽",
      "body": "美股三大指數表現穩定，S&P 500漲0.37%，NASDAQ漲0.19%，DOW漲0.58%。VIX下跌0.66%，顯示市場風險偏好略增。匯率方面，台幣對美元小幅走弱。這些國際局勢對台股的影響不大，台股仍然以內盤走勢為主。"
    },
    {
      "heading": "台股盤勢重點",
      "body": "台股加權指數上漲0.09%，成交量仍然偏低。三大法人買超自營商和投信，外資買超。今日多空研判，台股仍然處於多頭行情，但需要注意量能的不足。"
    },
    {
      "heading": "熱門族群與個股",
      "body": "電子產業領漲，聯發科上漲4.24%，中興電上漲6.56%。其他個股如華邦電、力積電等也表現良好。這些個股的漲幅主要歸因於產業內的基本面改善和市場需求的增長。"
    },
    {
      "heading": "自選股體檢",
      "body": "讓我們逐一檢視自選股。中興電漲6.56%，技術面強勁，RSI指標為69.74。聯發科漲4.24%，基本面良好，預計未來表現繼續優異。另外，南亞漲4.82%，量能增加，顯示市場對其信心增強。"
    },
    {
      "heading": "個股新聞追蹤",
      "body": "中興電近期無相關新聞。但根據我們之前的報導，中興電的基本面改善和市場需求的增強，將推動其未來的發展。"
    },
    {
      "heading": "今日操作建議",
      "body": "今日操作建議是繼續關注電子產業的個股，如聯發科、中興電等。同時需要注意量能的不足，建議投資者謹慎操作。"
    }
  ],
  "risk_alerts": [
    "量能不足可能導致市場波動加大",
    "個股漲幅過大可能會出現回調"
  ],
  "closing": "這就是今天『台股盤中快訊』的全部內容，感謝您的收看。請繼續關注市場的動態，謹慎操作，祝您投資順利。",
  "status": "success",
  "timestamp": "2026-05-26 10:12:36",
  "model_used": "groq:llama-3.3-70b-versatile"
}