{
  "date": "20260427",
  "fetched_at": "2026-04-27 19:40:01",
  "foreign_buy_top": [
    {
      "code": "2408",
      "symbol": "2408.TW",
      "name": "南亞科",
      "foreign": 36559346,
      "trust": 60085,
      "dealer": 1963769,
      "total": 38583200,
      "close": 206.0,
      "change_pct": -0.96,
      "volume": 99650668
    },
    {
      "code": "2337",
      "symbol": "2337.TW",
      "name": "旺宏",
      "foreign": 29694190,
      "trust": 367000,
      "dealer": 1838240,
      "total": 31899430,
      "close": 132.0,
      "change_pct": 4.76,
      "volume": 150260221
    },
    {
      "code": "00878",
      "symbol": "00878.TW",
      "name": "國泰永續高股息",
      "foreign": 27017273,
      "trust": 0,
      "dealer": 39488678,
      "total": 66505951,
      "close": 25.0,
      "change_pct": 1.38,
      "volume": 83418253
    },
    {
      "code": "2317",
      "symbol": "2317.TW",
      "name": "鴻海",
      "foreign": 19578926,
      "trust": 3561514,
      "dealer": 1343266,
      "total": 24483706,
      "close": 221.5,
      "change_pct": -1.56,
      "volume": 77230253
    },
    {
      "code": "00712",
      "symbol": "00712.TW",
      "name": "復華富時不動產",
      "foreign": 16829025,
      "trust": 0,
      "dealer": 14884421,
      "total": 31713446,
      "close": 9.01,
      "change_pct": -0.11,
      "volume": 14919003
    },
    {
      "code": "0056",
      "symbol": "0056.TW",
      "name": "元大高股息",
      "foreign": 16311025,
      "trust": -33559000,
      "dealer": 67164128,
      "total": 49916153,
      "close": 40.95,
      "change_pct": 0.74,
      "volume": 67087826
    },
    {
      "code": "2887",
      "symbol": "2887.TW",
      "name": "台新新光金",
      "foreign": 14784345,
      "trust": -18127688,
      "dealer": -1805962,
      "total": -5149305,
      "close": 23.95,
      "change_pct": 1.05,
      "volume": 72816321
    },
    {
      "code": "2883",
      "symbol": "2883.TW",
      "name": "凱基金",
      "foreign": 12151796,
      "trust": -520596,
      "dealer": -2882459,
      "total": 8748741,
      "close": 20.3,
      "change_pct": 0.5,
      "volume": 36536564
    },
    {
      "code": "2884",
      "symbol": "2884.TW",
      "name": "玉山金",
      "foreign": 11866837,
      "trust": -5484170,
      "dealer": -2043790,
      "total": 4338877,
      "close": 32.55,
      "change_pct": 0.31,
      "volume": 38407291
    },
    {
      "code": "2344",
      "symbol": "2344.TW",
      "name": "華邦電",
      "foreign": 11770458,
      "trust": 17767242,
      "dealer": 1170232,
      "total": 30707932,
      "close": 88.2,
      "change_pct": 0.46,
      "volume": 122540288
    }
  ],
  "foreign_sell_top": [
    {
      "code": "009816",
      "symbol": "009816.TW",
      "name": "凱基台灣TOP50",
      "foreign": -46316850,
      "trust": 0,
      "dealer": -87845699,
      "total": -134162549,
      "close": 12.87,
      "change_pct": 3.87,
      "volume": 206192629
    },
    {
      "code": "2002",
      "symbol": "2002.TW",
      "name": "中鋼",
      "foreign": -37952329,
      "trust": -130558,
      "dealer": -609405,
      "total": -38692292,
      "close": 19.0,
      "change_pct": -0.78,
      "volume": 44297648
    },
    {
      "code": "2409",
      "symbol": "2409.TW",
      "name": "友達",
      "foreign": -37482213,
      "trust": -11019,
      "dealer": 453301,
      "total": -37039931,
      "close": 17.2,
      "change_pct": -3.1,
      "volume": 203074622
    },
    {
      "code": "0052",
      "symbol": "0052.TW",
      "name": "富邦科技",
      "foreign": -24998996,
      "trust": 238000,
      "dealer": -5852131,
      "total": -30613127,
      "close": 52.7,
      "change_pct": 4.67,
      "volume": 71251696
    },
    {
      "code": "2303",
      "symbol": "2303.TW",
      "name": "聯電",
      "foreign": -19286246,
      "trust": -9991857,
      "dealer": -7061835,
      "total": -36339938,
      "close": 74.5,
      "change_pct": 1.22,
      "volume": 180527350
    },
    {
      "code": "2330",
      "symbol": "2330.TW",
      "name": "台積電",
      "foreign": -18940165,
      "trust": 4992808,
      "dealer": 248266,
      "total": -13699091,
      "close": 2185.0,
      "change_pct": 5.05,
      "volume": 52391785
    },
    {
      "code": "00940",
      "symbol": "00940.TW",
      "name": "元大台灣價值高息",
      "foreign": -13577981,
      "trust": 0,
      "dealer": 72968060,
      "total": 59390079,
      "close": 10.32,
      "change_pct": 0.19,
      "volume": 73468602
    },
    {
      "code": "2356",
      "symbol": "2356.TW",
      "name": "英業達",
      "foreign": -13230265,
      "trust": -558016,
      "dealer": -1151708,
      "total": -14939989,
      "close": 48.1,
      "change_pct": 3.89,
      "volume": 44404388
    },
    {
      "code": "0050",
      "symbol": "0050.TW",
      "name": "元大台灣50",
      "foreign": -9654843,
      "trust": 2048000,
      "dealer": -16316533,
      "total": -23923376,
      "close": 89.95,
      "change_pct": 4.17,
      "volume": 129885911
    },
    {
      "code": "3189",
      "symbol": "3189.TW",
      "name": "景碩",
      "foreign": -9632811,
      "trust": 338000,
      "dealer": -115092,
      "total": -9409903,
      "close": 526.0,
      "change_pct": 9.81,
      "volume": 57209204
    }
  ],
  "trust_buy_top": [
    {
      "code": "2344",
      "symbol": "2344.TW",
      "name": "華邦電",
      "foreign": 11770458,
      "trust": 17767242,
      "dealer": 1170232,
      "total": 30707932,
      "close": 88.2,
      "change_pct": 0.46,
      "volume": 122540288
    },
    {
      "code": "2330",
      "symbol": "2330.TW",
      "name": "台積電",
      "foreign": -18940165,
      "trust": 4992808,
      "dealer": 248266,
      "total": -13699091,
      "close": 2185.0,
      "change_pct": 5.05,
      "volume": 52391785
    },
    {
      "code": "4958",
      "symbol": "4958.TW",
      "name": "臻鼎-KY",
      "foreign": -9467425,
      "trust": 4191607,
      "dealer": -111998,
      "total": -5387816,
      "close": 347.5,
      "change_pct": 6.92,
      "volume": 102168352
    },
    {
      "code": "2317",
      "symbol": "2317.TW",
      "name": "鴻海",
      "foreign": 19578926,
      "trust": 3561514,
      "dealer": 1343266,
      "total": 24483706,
      "close": 221.5,
      "change_pct": -1.56,
      "volume": 77230253
    },
    {
      "code": "0050",
      "symbol": "0050.TW",
      "name": "元大台灣50",
      "foreign": -9654843,
      "trust": 2048000,
      "dealer": -16316533,
      "total": -23923376,
      "close": 89.95,
      "change_pct": 4.17,
      "volume": 129885911
    },
    {
      "code": "8046",
      "symbol": "8046.TW",
      "name": "南電",
      "foreign": -5465604,
      "trust": 1362003,
      "dealer": 6213,
      "total": -4097388,
      "close": 874.0,
      "change_pct": 9.94,
      "volume": 22699037
    },
    {
      "code": "6669",
      "symbol": "6669.TW",
      "name": "緯穎",
      "foreign": -1357764,
      "trust": 1087787,
      "dealer": 39430,
      "total": -230547,
      "close": 4635.0,
      "change_pct": 9.06,
      "volume": 5019268
    },
    {
      "code": "00881",
      "symbol": "00881.TW",
      "name": "國泰台灣科技龍頭",
      "foreign": -1570070,
      "trust": 800000,
      "dealer": -1222989,
      "total": -1993059,
      "close": 45.9,
      "change_pct": 3.82,
      "volume": 20610778
    },
    {
      "code": "2345",
      "symbol": "2345.TW",
      "name": "智邦",
      "foreign": -207779,
      "trust": 725261,
      "dealer": 29155,
      "total": 546637,
      "close": 2140.0,
      "change_pct": 2.88,
      "volume": 5127676
    },
    {
      "code": "2368",
      "symbol": "2368.TW",
      "name": "金像電",
      "foreign": -1123385,
      "trust": 722546,
      "dealer": -100828,
      "total": -501667,
      "close": 1390.0,
      "change_pct": 9.88,
      "volume": 8735359
    }
  ],
  "total_buy_top": [
    {
      "code": "00878",
      "symbol": "00878.TW",
      "name": "國泰永續高股息",
      "foreign": 27017273,
      "trust": 0,
      "dealer": 39488678,
      "total": 66505951,
      "close": 25.0,
      "change_pct": 1.38,
      "volume": 83418253
    },
    {
      "code": "00940",
      "symbol": "00940.TW",
      "name": "元大台灣價值高息",
      "foreign": -13577981,
      "trust": 0,
      "dealer": 72968060,
      "total": 59390079,
      "close": 10.32,
      "change_pct": 0.19,
      "volume": 73468602
    },
    {
      "code": "0056",
      "symbol": "0056.TW",
      "name": "元大高股息",
      "foreign": 16311025,
      "trust": -33559000,
      "dealer": 67164128,
      "total": 49916153,
      "close": 40.95,
      "change_pct": 0.74,
      "volume": 67087826
    },
    {
      "code": "2408",
      "symbol": "2408.TW",
      "name": "南亞科",
      "foreign": 36559346,
      "trust": 60085,
      "dealer": 1963769,
      "total": 38583200,
      "close": 206.0,
      "change_pct": -0.96,
      "volume": 99650668
    },
    {
      "code": "00919",
      "symbol": "00919.TW",
      "name": "群益台灣精選高息",
      "foreign": -1984356,
      "trust": 0,
      "dealer": 37427332,
      "total": 35442976,
      "close": 23.5,
      "change_pct": 0.21,
      "volume": 98325664
    },
    {
      "code": "2337",
      "symbol": "2337.TW",
      "name": "旺宏",
      "foreign": 29694190,
      "trust": 367000,
      "dealer": 1838240,
      "total": 31899430,
      "close": 132.0,
      "change_pct": 4.76,
      "volume": 150260221
    },
    {
      "code": "00712",
      "symbol": "00712.TW",
      "name": "復華富時不動產",
      "foreign": 16829025,
      "trust": 0,
      "dealer": 14884421,
      "total": 31713446,
      "close": 9.01,
      "change_pct": -0.11,
      "volume": 14919003
    },
    {
      "code": "2344",
      "symbol": "2344.TW",
      "name": "華邦電",
      "foreign": 11770458,
      "trust": 17767242,
      "dealer": 1170232,
      "total": 30707932,
      "close": 88.2,
      "change_pct": 0.46,
      "volume": 122540288
    },
    {
      "code": "00929",
      "symbol": "00929.TW",
      "name": "復華台灣科技優息",
      "foreign": 4357262,
      "trust": 0,
      "dealer": 20911820,
      "total": 25269082,
      "close": 22.2,
      "change_pct": 1.65,
      "volume": 69495534
    },
    {
      "code": "2317",
      "symbol": "2317.TW",
      "name": "鴻海",
      "foreign": 19578926,
      "trust": 3561514,
      "dealer": 1343266,
      "total": 24483706,
      "close": 221.5,
      "change_pct": -1.56,
      "volume": 77230253
    }
  ],
  "total_sell_top": [
    {
      "code": "009816",
      "symbol": "009816.TW",
      "name": "凱基台灣TOP50",
      "foreign": -46316850,
      "trust": 0,
      "dealer": -87845699,
      "total": -134162549,
      "close": 12.87,
      "change_pct": 3.87,
      "volume": 206192629
    },
    {
      "code": "009819",
      "symbol": "009819.TW",
      "name": "中信數據及電力",
      "foreign": -856240,
      "trust": 0,
      "dealer": -102174496,
      "total": -103030736,
      "close": 10.89,
      "change_pct": -13.16,
      "volume": 170265430
    },
    {
      "code": "2002",
      "symbol": "2002.TW",
      "name": "中鋼",
      "foreign": -37952329,
      "trust": -130558,
      "dealer": -609405,
      "total": -38692292,
      "close": 19.0,
      "change_pct": -0.78,
      "volume": 44297648
    },
    {
      "code": "2409",
      "symbol": "2409.TW",
      "name": "友達",
      "foreign": -37482213,
      "trust": -11019,
      "dealer": 453301,
      "total": -37039931,
      "close": 17.2,
      "change_pct": -3.1,
      "volume": 203074622
    },
    {
      "code": "2303",
      "symbol": "2303.TW",
      "name": "聯電",
      "foreign": -19286246,
      "trust": -9991857,
      "dealer": -7061835,
      "total": -36339938,
      "close": 74.5,
      "change_pct": 1.22,
      "volume": 180527350
    },
    {
      "code": "0052",
      "symbol": "0052.TW",
      "name": "富邦科技",
      "foreign": -24998996,
      "trust": 238000,
      "dealer": -5852131,
      "total": -30613127,
      "close": 52.7,
      "change_pct": 4.67,
      "volume": 71251696
    },
    {
      "code": "0050",
      "symbol": "0050.TW",
      "name": "元大台灣50",
      "foreign": -9654843,
      "trust": 2048000,
      "dealer": -16316533,
      "total": -23923376,
      "close": 89.95,
      "change_pct": 4.17,
      "volume": 129885911
    },
    {
      "code": "2356",
      "symbol": "2356.TW",
      "name": "英業達",
      "foreign": -13230265,
      "trust": -558016,
      "dealer": -1151708,
      "total": -14939989,
      "close": 48.1,
      "change_pct": 3.89,
      "volume": 44404388
    },
    {
      "code": "2330",
      "symbol": "2330.TW",
      "name": "台積電",
      "foreign": -18940165,
      "trust": 4992808,
      "dealer": 248266,
      "total": -13699091,
      "close": 2185.0,
      "change_pct": 5.05,
      "volume": 52391785
    },
    {
      "code": "2891",
      "symbol": "2891.TW",
      "name": "中信金",
      "foreign": 3171769,
      "trust": -11591550,
      "dealer": -2149231,
      "total": -10569012,
      "close": 52.9,
      "change_pct": 0.38,
      "volume": 38226379
    }
  ],
  "price_up_top": [
    {
      "code": "8028",
      "symbol": "8028.TW",
      "name": "昇陽半導體",
      "close": 242.0,
      "change": 22.0,
      "change_pct": 10.0,
      "volume": 23754243,
      "value": 5720737623
    },
    {
      "code": "8210",
      "symbol": "8210.TW",
      "name": "勤誠",
      "close": 1210.0,
      "change": 110.0,
      "change_pct": 10.0,
      "volume": 5363957,
      "value": 6406789725
    },
    {
      "code": "3209",
      "symbol": "3209.TW",
      "name": "全科",
      "close": 54.5,
      "change": 4.95,
      "change_pct": 9.99,
      "volume": 13248712,
      "value": 711805211
    },
    {
      "code": "6861",
      "symbol": "6861.TW",
      "name": "睿生光電",
      "close": 259.0,
      "change": 23.5,
      "change_pct": 9.98,
      "volume": 2107986,
      "value": 531819391
    },
    {
      "code": "1727",
      "symbol": "1727.TW",
      "name": "中華化",
      "close": 70.7,
      "change": 6.4,
      "change_pct": 9.95,
      "volume": 24145751,
      "value": 1652474775
    },
    {
      "code": "2399",
      "symbol": "2399.TW",
      "name": "映泰",
      "close": 43.65,
      "change": 3.95,
      "change_pct": 9.95,
      "volume": 49139699,
      "value": 2089378212
    },
    {
      "code": "6658",
      "symbol": "6658.TW",
      "name": "聯策",
      "close": 110.5,
      "change": 10.0,
      "change_pct": 9.95,
      "volume": 8773691,
      "value": 942570770
    },
    {
      "code": "6108",
      "symbol": "6108.TW",
      "name": "競國",
      "close": 19.35,
      "change": 1.75,
      "change_pct": 9.94,
      "volume": 6281934,
      "value": 120407283
    },
    {
      "code": "8046",
      "symbol": "8046.TW",
      "name": "南電",
      "close": 874.0,
      "change": 79.0,
      "change_pct": 9.94,
      "volume": 22699037,
      "value": 19652093707
    },
    {
      "code": "2429",
      "symbol": "2429.TW",
      "name": "銘旺科",
      "close": 60.9,
      "change": 5.5,
      "change_pct": 9.93,
      "volume": 4521022,
      "value": 267860428
    }
  ],
  "price_down_top": [
    {
      "code": "009819",
      "symbol": "009819.TW",
      "name": "中信數據及電力",
      "close": 10.89,
      "change": -1.65,
      "change_pct": -13.16,
      "volume": 170265430,
      "value": 1847009273
    },
    {
      "code": "6451",
      "symbol": "6451.TW",
      "name": "訊芯-KY",
      "close": 402.0,
      "change": -44.5,
      "change_pct": -9.97,
      "volume": 1408319,
      "value": 579361326
    },
    {
      "code": "4739",
      "symbol": "4739.TW",
      "name": "康普",
      "close": 90.5,
      "change": -10.0,
      "change_pct": -9.95,
      "volume": 10647278,
      "value": 991424380
    },
    {
      "code": "1711",
      "symbol": "1711.TW",
      "name": "永光",
      "close": 50.9,
      "change": -5.6,
      "change_pct": -9.91,
      "volume": 8632432,
      "value": 442409686
    },
    {
      "code": "8271",
      "symbol": "8271.TW",
      "name": "宇瞻",
      "close": 200.0,
      "change": -22.0,
      "change_pct": -9.91,
      "volume": 1825476,
      "value": 370416114
    },
    {
      "code": "6426",
      "symbol": "6426.TW",
      "name": "統新",
      "close": 216.0,
      "change": -23.5,
      "change_pct": -9.81,
      "volume": 5213555,
      "value": 1196559493
    },
    {
      "code": "3138",
      "symbol": "3138.TW",
      "name": "耀登",
      "close": 157.0,
      "change": -16.5,
      "change_pct": -9.51,
      "volume": 4633020,
      "value": 750287002
    },
    {
      "code": "6919",
      "symbol": "6919.TW",
      "name": "康霈*",
      "close": 99.7,
      "change": -9.8,
      "change_pct": -8.95,
      "volume": 11152432,
      "value": 1154012186
    },
    {
      "code": "1721",
      "symbol": "1721.TW",
      "name": "三晃",
      "close": 27.3,
      "change": -2.65,
      "change_pct": -8.85,
      "volume": 7801494,
      "value": 214797194
    },
    {
      "code": "3583",
      "symbol": "3583.TW",
      "name": "辛耘",
      "close": 815.0,
      "change": -78.0,
      "change_pct": -8.73,
      "volume": 2338615,
      "value": 1952258563
    }
  ],
  "volume_surge_top": [],
  "chip_concentration_jump": [],
  "suspicious_buy_top": [
    {
      "code": "2103",
      "symbol": "2103.TW",
      "name": "台橡",
      "foreign": 3687503,
      "trust": -2000,
      "total": 4371951,
      "change_pct": -3.13,
      "close": 18.55,
      "volume": 3077309,
      "anomaly_type": "外資買超但下跌",
      "severity": 0.81,
      "hint": "可能為融券回補 / delta hedge / 借券還券 / ETF 套利 / 鉅額換手"
    },
    {
      "code": "3481",
      "symbol": "3481.TW",
      "name": "群創",
      "foreign": 10980325,
      "trust": -161451,
      "total": 13589548,
      "change_pct": -2.9,
      "close": 23.4,
      "volume": 233909107,
      "anomaly_type": "外資買超但下跌",
      "severity": 0.79,
      "hint": "可能為融券回補 / delta hedge / 借券還券 / ETF 套利 / 鉅額換手"
    },
    {
      "code": "1314",
      "symbol": "1314.TW",
      "name": "中石化",
      "foreign": 3840384,
      "trust": 0,
      "total": 3754642,
      "change_pct": -2.37,
      "close": 7.42,
      "volume": 17163761,
      "anomaly_type": "外資買超但下跌",
      "severity": 0.74,
      "hint": "可能為融券回補 / delta hedge / 借券還券 / ETF 套利 / 鉅額換手"
    }
  ],
  "recurring_3d": {
    "foreign_sell_top": [
      {
        "code": "2409",
        "streak": 3
      }
    ],
    "price_up_top": [
      {
        "code": "2429",
        "streak": 3
      },
      {
        "code": "8046",
        "streak": 3
      },
      {
        "code": "1727",
        "streak": 3
      },
      {
        "code": "8028",
        "streak": 3
      },
      {
        "code": "3209",
        "streak": 3
      },
      {
        "code": "8210",
        "streak": 3
      },
      {
        "code": "6861",
        "streak": 3
      },
      {
        "code": "2399",
        "streak": 3
      },
      {
        "code": "6108",
        "streak": 3
      },
      {
        "code": "6658",
        "streak": 3
      }
    ]
  }
}